geoverifysm/__init__.py
geoverifysm/nongui.py
geoverifysm/langchain_booth/__init__.py
geoverifysm/langchain_booth/baselines.py
geoverifysm/langchain_booth/overlap.py
geoverifysm/scraper/__init__.py
geoverifysm/scraper/constants.py
geoverifysm/scraper/level_scraper.py
geoverifysm/scraper/pack_scraper.py
geoverifysm/scraper/utils.py
test/__init__.py
geoverifysm-1.1.dist-info/LICENSE
geoverifysm-1.1.dist-info/METADATA
geoverifysm-1.1.dist-info/WHEEL
geoverifysm-1.1.dist-info/top_level.txt
geoverifysm-1.1.dist-info/RECORD
